obsidian_digest/__init__.py
obsidian_digest/obsidian_digest_cli.py
obsidian_digest-0.0.0.post1.dist-info/METADATA
obsidian_digest-0.0.0.post1.dist-info/WHEEL
obsidian_digest-0.0.0.post1.dist-info/entry_points.txt
obsidian_digest-0.0.0.post1.dist-info/top_level.txt
obsidian_digest-0.0.0.post1.dist-info/RECORD
